azure_openai_limits/__init__.py
azure_openai_limits/__main__.py
azure_openai_limits/api.py
azure_openai_limits/data.py
azure_openai_limits/models.json
azure_openai_limits/types.py
azure_openai_limits-0.1.2.dist-info/licenses/LICENSE
azure_openai_limits-0.1.2.dist-info/METADATA
azure_openai_limits-0.1.2.dist-info/WHEEL
azure_openai_limits-0.1.2.dist-info/entry_points.txt
azure_openai_limits-0.1.2.dist-info/top_level.txt
azure_openai_limits-0.1.2.dist-info/RECORD
