Metadata-Version: 2.4
Name: azure-openai-limits
Version: 0.1.2
Summary: Static token limits for Azure OpenAI models (context/output), with CLI.
Author-email: Taylor Nelson <your-email@example.com>
Maintainer-email: Taylor Nelson <your-email@example.com>
License-Expression: MIT
Project-URL: Homepage, https://github.com/taylorn-ai/azure-openai-limits
Project-URL: Repository, https://github.com/taylorn-ai/azure-openai-limits
Project-URL: Documentation, https://github.com/taylorn-ai/azure-openai-limits#readme
Project-URL: Issues, https://github.com/taylorn-ai/azure-openai-limits/issues
Project-URL: Changelog, https://github.com/taylorn-ai/azure-openai-limits/releases
Keywords: azure,openai,token-limits,gpt,ai,machine-learning
Classifier: Development Status :: 4 - Beta
Classifier: Intended Audience :: Developers
Classifier: Operating System :: OS Independent
Classifier: Programming Language :: Python :: 3
Classifier: Programming Language :: Python :: 3.10
Classifier: Programming Language :: Python :: 3.11
Classifier: Programming Language :: Python :: 3.12
Classifier: Topic :: Software Development :: Libraries :: Python Modules
Classifier: Topic :: Scientific/Engineering :: Artificial Intelligence
Requires-Python: >=3.10
License-File: LICENSE
Provides-Extra: dev
Requires-Dist: ruff==0.12.9; extra == "dev"
Requires-Dist: mypy==1.17.1; extra == "dev"
Requires-Dist: pytest==8.4.1; extra == "dev"
Requires-Dist: isort==6.0.1; extra == "dev"
Requires-Dist: pre-commit==4.3.0; extra == "dev"
Dynamic: license-file
